gradio_codeanalysisviewer/__init__.py
gradio_codeanalysisviewer/codeanalysisviewer.py
gradio_codeanalysisviewer/codeanalysisviewer.pyi
gradio_codeanalysisviewer/templates/component/index.js
gradio_codeanalysisviewer/templates/component/style.css
gradio_codeanalysisviewer/templates/example/index.js
gradio_codeanalysisviewer/templates/example/style.css
gradio_codeanalysisviewer-0.0.3.dist-info/METADATA
gradio_codeanalysisviewer-0.0.3.dist-info/WHEEL
gradio_codeanalysisviewer-0.0.3.dist-info/RECORD
