Metadata-Version: 2.4
Name: gradio_codeanalysisviewer
Version: 0.0.3
Summary: A nicer view to show the Agentic code analyser outputs
Author-email: Keshan <hello@keshan.dev>
License-Expression: MIT
Keywords: agents,agents-mcp-hackathon,code-analysis,custom-component-track,gradio-custom-component,gradio-template-SimpleTextbox
Classifier: Development Status :: 3 - Alpha
Classifier: Operating System :: OS Independent
Classifier: Programming Language :: Python :: 3
Classifier: Programming Language :: Python :: 3 :: Only
Classifier: Programming Language :: Python :: 3.8
Classifier: Programming Language :: Python :: 3.9
Classifier: Programming Language :: Python :: 3.10
Classifier: Programming Language :: Python :: 3.11
Classifier: Topic :: Scientific/Engineering
Classifier: Topic :: Scientific/Engineering :: Artificial Intelligence
Classifier: Topic :: Scientific/Engineering :: Visualization
Requires-Python: >=3.10
Requires-Dist: gradio<6.0,>=4.0
Provides-Extra: dev
Requires-Dist: build; extra == 'dev'
Requires-Dist: twine; extra == 'dev'
